.dockerignore
.eslintrc.js
.gitignore
AUTHORS
CHANGELOG.rst
LICENSE
MANIFEST.in
Makefile
README.rst
VERSION.txt
container-compose.yml
pyproject.toml
setup.cfg
setup.py
tox.ini
.github/workflows/dev-release.yaml
.github/workflows/distribution.yaml
.github/workflows/linter.yaml
.github/workflows/unittests.yaml
contrib/Vagrantfile.example
contrib/compose/web_custom_conf.py
contrib/compose/worker_custom_conf.py
contrib/conf/nitrate-httpd-vhosts.conf
contrib/conf/nitrate-httpd.conf
contrib/conf/nitrate-nginx.conf
contrib/devenv/devenv.sh
contrib/devenv/system.sh
contrib/scripts/adjust_mysql_auth_plugin.sh
contrib/scripts/build-artifacts-and-publish.sh
contrib/scripts/make-release.py
contrib/scripts/release-notes.tmpl.rst
contrib/scripts/templatelint.sh
docs/Makefile
docs/make.bat
docs/requirements.txt
docs/source/authors.rst
docs/source/conf.py
docs/source/configuration.rst
docs/source/contribution.rst
docs/source/index.rst
docs/source/license.rst
docs/source/report_issue.rst
docs/source/set_dev_env.rst
docs/source/set_dev_env_with_vagrant.rst
docs/source/_static/Add_Classification.png
docs/source/_static/Add_Component.png
docs/source/_static/Add_New_Group.png
docs/source/_static/Add_Priority.png
docs/source/_static/Add_Product.png
docs/source/_static/Add_TC_Category.png
docs/source/_static/Add_TP_Type.png
docs/source/_static/Add_Test_Build.png
docs/source/_static/Add_Version.png
docs/source/_static/Admin_Home.png
docs/source/_static/Advanced_Search.png
docs/source/_static/Auth_Home.png
docs/source/_static/BZ_Component.png
docs/source/_static/BZ_New_Bug.png
docs/source/_static/BZ_Other.png
docs/source/_static/BZ_TCMS.png
docs/source/_static/Case_Enter_Details.png
docs/source/_static/Cases_Home.png
docs/source/_static/Change_Status_Confirm.png
docs/source/_static/Click_Add.png
docs/source/_static/Click_Add_Cases_to_Run.png
docs/source/_static/Click_Add_To_Plan_Name.png
docs/source/_static/Click_Auth.png
docs/source/_static/Click_Cases.png
src/nitrate_tcms.egg-info/PKG-INFO
src/nitrate_tcms.egg-info/SOURCES.txt
src/nitrate_tcms.egg-info/dependency_links.txt
src/nitrate_tcms.egg-info/not-zip-safe
src/nitrate_tcms.egg-info/requires.txt
src/nitrate_tcms.egg-info/top_level.txt
