Metadata-Version: 2.1
Name: nitrate-tcms
Version: 4.13
Summary: A full-featured Test Case Management System
Home-page: https://github.com/Nitrate/Nitrate
Author: Nitrate Team
Maintainer: Chenxiong Qi
Maintainer-email: qcxhome@gmail.com
License: GPLv2+
Project-URL: Issue Tracker, https://github.com/Nitrate/Nitrate/issues
Project-URL: Source Code, https://github.com/Nitrate/Nitrate
Project-URL: Documentation, https://nitrate.readthedocs.io/
Project-URL: RPM Package, https://copr.fedorainfracloud.org/coprs/cqi/python-nitrate-tcms/
Project-URL: Release Notes, https://nitrate.readthedocs.io/en/latest/releases/
Project-URL: Container Images, https://quay.io/organization/nitrate
Keywords: test,case,plan,run
Platform: any
Classifier: Framework :: Django
Classifier: Framework :: Django :: 3.2
Classifier: Intended Audience :: Developers
Classifier: License :: OSI Approved :: GNU General Public License v2 or later (GPLv2+)
Classifier: Programming Language :: Python :: 3
Classifier: Programming Language :: Python :: 3.9
Classifier: Programming Language :: Python :: 3.10
Classifier: Programming Language :: Python :: 3 :: Only
Classifier: Topic :: Software Development :: Quality Assurance
Classifier: Topic :: Software Development :: Testing
Requires-Python: >=3.9
Provides-Extra: async
Provides-Extra: bugzilla
Provides-Extra: devtools
Provides-Extra: docs
Provides-Extra: krbauth
Provides-Extra: mysql
Provides-Extra: pgsql
Provides-Extra: socialauth
Provides-Extra: tests
